readligo.py
readligo-0.6.1.dist-info/LICENSE.txt
readligo-0.6.1.dist-info/METADATA
readligo-0.6.1.dist-info/WHEEL
readligo-0.6.1.dist-info/top_level.txt
readligo-0.6.1.dist-info/RECORD
