Metadata-Version: 2.1
Name: readligo
Version: 0.6.1
Summary: Tools for reading LIGO data files
Author: Roy Williams, Agata Trovato, Alan Weinstein
Author-email: Jonah Kanner <jonah.kanner@ligo.org>
Maintainer-email: Jonah Kanner <jonah.kanner@ligo.org>
License: Permission is hereby granted, free of charge, to any person obtaining a copy of this software and associated documentation files (the “Software”), to deal in the Software without restriction, including without limitation the rights to use, copy, modify, merge, publish, distribute, sublicense, and/or sell copies of the Software, and to permit persons to whom the Software is furnished to do so, subject to the following conditions:
Project-URL: homepage, https://git.ligo.org/gwosc/readligo
Project-URL: repository, https://git.ligo.org/gwosc/readligo
Keywords: ligo,gravitational waves,file format,astronomy
Requires-Python: >=3.7
License-File: LICENSE.txt
Requires-Dist: numpy>=1.17
